LICENSE
README.md
setup.py
pyquest_cffi/__init__.py
pyquest_cffi.egg-info/PKG-INFO
pyquest_cffi.egg-info/SOURCES.txt
pyquest_cffi.egg-info/dependency_links.txt
pyquest_cffi.egg-info/not-zip-safe
pyquest_cffi.egg-info/requires.txt
pyquest_cffi.egg-info/top_level.txt
pyquest_cffi/cheat/__init__.py
pyquest_cffi/cheat/initialization.py
pyquest_cffi/cheat/measurement.py
pyquest_cffi/cheat/test_initialization.py
pyquest_cffi/cheat/test_measurement.py
pyquest_cffi/ops/__init__.py
pyquest_cffi/ops/errors.py
pyquest_cffi/ops/ops.py
pyquest_cffi/ops/test_errors.py
pyquest_cffi/ops/test_ops.py
pyquest_cffi/questlib/__init__.py
pyquest_cffi/questlib/_abstract.py
pyquest_cffi/questlib/build_quest.py
pyquest_cffi/utils/__init__.py
pyquest_cffi/utils/dataoperation.py
pyquest_cffi/utils/reporting.py
pyquest_cffi/utils/test_utils.py