Metadata-Version: 2.1
Name: pyquest-cffi
Version: 3.2.3.1
Summary: Provides: Interactive python interface to QuEST quantum simulation toolkit;  Compile functionality, create, build and import valid QuEST source code from python
Home-page: UNKNOWN
Author: HQS Quantum Simulations: Sebastian Zanker, Nicolas Vogt
Author-email: info@quantumsimulations.de
License: Apache License 2.0
Download-URL: https://github.com/HQSquantumsimulations/PyQuEST-cffi/archive/3.2.3.tar.gz
Platform: UNKNOWN
Requires-Python: >=3.6
